Metadata-Version: 1.1
Name: bitrix
Version: 0.0.3
Summary: Bitrix24 python library
Home-page: https://github.com/NursErgesh/bitrix.git
Author: Noors Ergesh
Author-email: jackmovies01@gmail.com
License: MIT
Platform: UNKNOWN
Classifier: Development Status :: 4 - Beta
Classifier: Environment :: Web Environment
Classifier: Framework :: Django
Classifier: Framework :: Django
Classifier: Framework :: Django :: 1.11
Classifier: Framework :: Django :: 2.0
Classifier: Intended Audience :: Developers
Classifier: Operating System :: OS Independent
Classifier: Programming Language :: Python
Classifier: Programming Language :: Python :: 3.4
Classifier: Programming Language :: Python :: 3.5
Classifier: Programming Language :: Python :: 3.6
Classifier: Topic :: Software Development
Classifier: Topic :: Software Development :: Libraries :: Application Frameworks
